.coveragerc
.testr.conf
AUTHORS
COPYING
ChangeLog
HACKING.rst
LICENSE
LINKS
README.rst
requirements.txt
setup.cfg
setup.py
test-requirements.txt
tox.ini
dstat_plugins/__init__.py
dstat_plugins/version.py
dstat_plugins.egg-info/PKG-INFO
dstat_plugins.egg-info/SOURCES.txt
dstat_plugins.egg-info/dependency_links.txt
dstat_plugins.egg-info/entry_points.txt
dstat_plugins.egg-info/not-zip-safe
dstat_plugins.egg-info/pbr.json
dstat_plugins.egg-info/requires.txt
dstat_plugins.egg-info/top_level.txt
dstat_plugins/plugins/__init__.py
dstat_plugins/plugins/dstat_battery.py
dstat_plugins/plugins/dstat_battery_remain.py
dstat_plugins/plugins/dstat_condor_queue.py
dstat_plugins/plugins/dstat_cpufreq.py
dstat_plugins/plugins/dstat_dbus.py
dstat_plugins/plugins/dstat_disk_avgqu.py
dstat_plugins/plugins/dstat_disk_avgrq.py
dstat_plugins/plugins/dstat_disk_svctm.py
dstat_plugins/plugins/dstat_disk_tps.py
dstat_plugins/plugins/dstat_disk_util.py
dstat_plugins/plugins/dstat_disk_wait.py
dstat_plugins/plugins/dstat_dstat.py
dstat_plugins/plugins/dstat_dstat_cpu.py
dstat_plugins/plugins/dstat_dstat_ctxt.py
dstat_plugins/plugins/dstat_dstat_mem.py
dstat_plugins/plugins/dstat_fan.py
dstat_plugins/plugins/dstat_freespace.py
dstat_plugins/plugins/dstat_fuse.py
dstat_plugins/plugins/dstat_gpfs.py
dstat_plugins/plugins/dstat_gpfs_ops.py
dstat_plugins/plugins/dstat_helloworld.py
dstat_plugins/plugins/dstat_innodb_buffer.py
dstat_plugins/plugins/dstat_innodb_io.py
dstat_plugins/plugins/dstat_innodb_ops.py
dstat_plugins/plugins/dstat_lustre.py
dstat_plugins/plugins/dstat_md_status.py
dstat_plugins/plugins/dstat_memcache_hits.py
dstat_plugins/plugins/dstat_mysql5_cmds.py
dstat_plugins/plugins/dstat_mysql5_conn.py
dstat_plugins/plugins/dstat_mysql5_innodb.py
dstat_plugins/plugins/dstat_mysql5_innodb_basic.py
dstat_plugins/plugins/dstat_mysql5_innodb_extra.py
dstat_plugins/plugins/dstat_mysql5_io.py
dstat_plugins/plugins/dstat_mysql5_keys.py
dstat_plugins/plugins/dstat_mysql_io.py
dstat_plugins/plugins/dstat_mysql_keys.py
dstat_plugins/plugins/dstat_net_packets.py
dstat_plugins/plugins/dstat_nfs3.py
dstat_plugins/plugins/dstat_nfs3_ops.py
dstat_plugins/plugins/dstat_nfsd3.py
dstat_plugins/plugins/dstat_nfsd3_ops.py
dstat_plugins/plugins/dstat_nfsd4_ops.py
